miniscrapes/__init__.py
miniscrapes/cli.py
miniscrapes/config.py
miniscrapes/execution.py
miniscrapes/handlers.py
miniscrapes/scrapers.py
miniscrapes-0.1.7.dist-info/AUTHORS.rst
miniscrapes-0.1.7.dist-info/LICENSE
miniscrapes-0.1.7.dist-info/METADATA
miniscrapes-0.1.7.dist-info/WHEEL
miniscrapes-0.1.7.dist-info/entry_points.txt
miniscrapes-0.1.7.dist-info/top_level.txt
miniscrapes-0.1.7.dist-info/RECORD
