Metadata-Version: 2.1
Name: miniscrapes
Version: 0.1.7
Summary: lil' pieces of data, one miniscrape at a time
Home-page: https://github.com/marcua/miniscrapes
Author: Adam Marcus
Author-email: marcua@marcua.net
License: Apache Software License 2.0
Keywords: miniscrapes
Platform: UNKNOWN
Classifier: Development Status :: 2 - Pre-Alpha
Classifier: Intended Audience :: Developers
Classifier: License :: OSI Approved :: Apache Software License
Classifier: Natural Language :: English
Classifier: Programming Language :: Python :: 3
Classifier: Programming Language :: Python :: 3.5
Classifier: Programming Language :: Python :: 3.6
Classifier: Programming Language :: Python :: 3.7
Classifier: Programming Language :: Python :: 3.8
Requires-Python: >=3.5
Requires-Dist: Click (>=7.0)
Requires-Dist: dpath (==2.0.1)
Requires-Dist: duckdb (==0.3.2)
Requires-Dist: pytomlpp (==0.3.5)
Requires-Dist: pyzipcode (==2.0.0)
Requires-Dist: requests (==2.25.1)
